Johnson_iVerilog/DFlipFlop.v
/***********************************************************************************************
	EE 371
	Joshua Smith
	Section AB

    Description:
        DFlipFlop.v is a simple D Flip Flop with asynchronous reset.

    Inputs:
        D: The input of the DFF
        clk: The clock signal, the rising edge of which triggers the DFF
        rst: The reset signal, which is asynchronous from the clock

    Outputs:
        q: The output of the DFF, which takes the value of D upon every clock edge
        qBar: the inverse of the q signal

	Author: Joshua Shackelford

***********************************************************************************************/

module DFlipFlop (q, qBar, D, clk, rst);
	input clk, rst, D;
	output q, qBar;
	
	reg q;
	not n1 (qBar, q);
	
	always @(negedge rst or posedge clk) //negedge for rst as it is active-low reset
	begin
		if(!rst)
			q = 0;
		else
			q = D;
	end

endmodule

Johnson_iVerilog/Johnson.v
/***********************************************************************************************
	EE 371
	Joshua Smith
	Section AB

    Description:
        Johnson.v is a behavioral model implementation of a Johnson Ring counter. The Johnson
        counter is interesting in that it does not count straight from 0 to 15, but rather
        follows the following sequence: 0,1,3,7,15,14,12,8,0 and repeats.

    Inputs:
        clk: The clock signal, the rising edge of which triggers the DFFs within the counter
        rst: The reset signal, which is asynchronous from the clock

    Outputs:
        outBus: a 4-bit bus that carries the counting signal of this Ring counter

	Contributors: Titus Berndt, Nesta Isakovic, and Joshua Shackelford

***********************************************************************************************/

`include "DFlipFlop.v"

module Johnson (clk, rst, outBus);

    input clk, rst;
    output [3:0] outBus;

    //Wires between DFFs
    wire [3:0] link;

    //Set the behavior system regarding the outBus
    assign link[0] = ~outBus[3];
    assign link[1] = outBus[0];
    assign link[2] = outBus[1];
    assign link[3] = outBus[2];

    //Set all the appropriate DFlipFlops using a generate statement
    genvar i;
    generate
        for(i = 0; i < 4; i = i+1) begin : eachDFF
            DFlipFlop otherDFF (.q(outBus[i]), .D(link[i]), .clk(clk), .rst(rst));
        end
    endgenerate

endmodule

Johnson_iVerilog/Johnson_testbench.v
/***********************************************************************************************
	EE 371
	Joshua Smith
	Section AB

    Description:
        Johnson_testbench.v is the tester module for the Johnson counter. Simply setting the
        right inputs and outputs and then toggling the reset and allowing the counter to go
        for several cycles before toggling the reset again.

    Inputs:
        None

    Outputs:
        None
        
	Contributors: Titus Berndt, Nesta Isakovic, and Joshua Shackelford

***********************************************************************************************/


`include "Johnson.v"

module Johnson_testbench();

    reg clk, rst;
    wire [3:0] outBus;
    parameter CLOCK_PERIOD = 10;

    initial clk <= 1'b0;
    always #(CLOCK_PERIOD/2) clk <= ~clk;

    Johnson dut (clk, rst, outBus);

    initial begin
        $dumpfile("John.vcd");
        $dumpvars(1, dut);
    end

    initial begin
        rst <= 0;       #10;
        rst <= 1;       #10;
        repeat(50)      #10;
        rst <= 0;       #10;
        rst <= 1;       #10;
        repeat(17)      #10;
        $finish();
    end

endmodule

Johnson_iVerilog/John.vcd
$date
	Mon Apr 10 12:44:49 2017
$end
$version
	Icarus Verilog
$end
$timescale
	1s
$end
$scope module Johnson_testbench $end
$scope module dut $end
$var wire 1 ! clk $end
$var wire 1 " rst $end
$var wire 4 # outBus [3:0] $end
$var wire 4 $ link [3:0] $end
$upscope $end
$upscope $end
$enddefinitions $end
#0
$dumpvars
b1 $
b0 #
0"
0!
$end
#5
1!
#10
0!
1"
#15
b11 $
b1 #
1!
#20
0!
#25
b111 $
b11 #
1!
#30
0!
#35
b1111 $
b111 #
1!
#40
0!
#45
b1110 $
b1111 #
1!
#50
0!
#55
b1100 $
b1110 #
1!
#60
0!
#65
b1000 $
b1100 #
1!
#70
0!
#75
b0 $
b1000 #
1!
#80
0!
#85
b1 $
b0 #
1!
#90
0!
#95
b11 $
b1 #
1!
#100
0!
#105
b111 $
b11 #
1!
#110
0!
#115
b1111 $
b111 #
1!
#120
0!
#125
b1110 $
b1111 #
1!
#130
0!
#135
b1100 $
b1110 #
1!
#140
0!
#145
b1000 $
b1100 #
1!
#150
0!
#155
b0 $
b1000 #
1!
#160
0!
#165
b1 $
b0 #
1!
#170
0!
#175
b11 $
b1 #
1!
#180
0!
#185
b111 $
b11 #
1!
#190
0!
#195
b1111 $
b111 #
1!
#200
0!
#205
b1110 $
b1111 #
1!
#210
0!
#215
b1100 $
b1110 #
1!
#220
0!
#225
b1000 $
b1100 #
1!
#230
0!
#235
b0 $
b1000 #
1!
#240
0!
#245
b1 $
b0 #
1!
#250
0!
#255
b11 $
b1 #
1!
#260
0!
#265
b111 $
b11 #
1!
#270
0!
#275
b1111 $
b111 #
1!
#280
0!
#285
b1110 $
b1111 #
1!
#290
0!
#295
b1100 $
b1110 #
1!
#300
0!
#305
b1000 $
b1100 #
1!
#310
0!
#315
b0 $
b1000 #
1!
#320
0!
#325
b1 $
b0 #
1!
#330
0!
#335
b11 $
b1 #
1!
#340
0!
#345
b111 $
b11 #
1!
#350
0!
#355
b1111 $
b111 #
1!
#360
0!
#365
b1110 $
b1111 #
1!
#370
0!
#375
b1100 $
b1110 #
1!
#380
0!
#385
b1000 $
b1100 #
1!
#390
0!
#395
b0 $
b1000 #
1!
#400
0!
#405
b1 $
b0 #
1!
#410
0!
#415
b11 $
b1 #
1!
#420
0!
#425
b111 $
b11 #
1!
#430
0!
#435
b1111 $
b111 #
1!
#440
0!
#445
b1110 $
b1111 #
1!
#450
0!
#455
b1100 $
b1110 #
1!
#460
0!
#465
b1000 $
b1100 #
1!
#470
0!
#475
b0 $
b1000 #
1!
#480
0!
#485
b1 $
b0 #
1!
#490
0!
#495
b11 $
b1 #
1!
#500
0!
#505
b111 $
b11 #
1!
#510
0!
#515
b1111 $
b111 #
1!
#520
b1 $
b0 #
0!
0"
#525
1!
#530
0!
1"
#535
b11 $
b1 #
1!
#540
0!
#545
b111 $
b11 #
1!
#550
0!
#555
b1111 $
b111 #
1!
#560
0!
#565
b1110 $
b1111 #
1!
#570
0!
#575
b1100 $
b1110 #
1!
#580
0!
#585
b1000 $
b1100 #
1!
#590
0!
#595
b0 $
b1000 #
1!
#600
0!
#605
b1 $
b0 #
1!
#610
0!
#615
b11 $
b1 #
1!
#620
0!
#625
b111 $
b11 #
1!
#630
0!
#635
b1111 $
b111 #
1!
#640
0!
#645
b1110 $
b1111 #
1!
#650
0!
#655
b1100 $
b1110 #
1!
#660
0!
#665
b1000 $
b1100 #
1!
#670
0!
#675
b0 $
b1000 #
1!
#680
0!
#685
b1 $
b0 #
1!
#690
0!
#695
b11 $
b1 #
1!
#700
0!
#705
b111 $
b11 #
1!
