Ripple_iVerilog/DFlipFlop.v
/***********************************************************************************************
	EE 371
	Joshua Smith
	Section AB

	Description:
		DFlipFlop.v is a simple D Flip Flop with asynchronous reset.

	Inputs:
		D: The input of the DFF
		clk: The clock signal, the rising edge of which triggers the DFF
		rst: The reset signal, which is asynchronous from the clock

	Outputs:
		q: The output of the DFF, which takes the value of D upon every clock edge
		qBar: the inverse of the q signal

	Contributors: Titus Berndt, Nesta Isakovic, and Joshua Shackelford

***********************************************************************************************/

module DFlipFlop (q, qBar, D, clk, rst);
	input clk, rst, D;
	output q, qBar;
	
	reg q;
	not n1 (qBar, q);
	
	always @(negedge rst or posedge clk) //negedge for rst as it is active-low reset
	begin
		if(!rst)
			q = 0;
		else
			q = D;
	end

endmodule

Ripple_iVerilog/RippleUp_Top.v
/***********************************************************************************************
	EE 371
	Joshua Smith
	Section AB

	Description:
		RippleUp_Top.v is the top level module for a basic 4-bit Asynchronous (or Ripple) Up Counter.
		The System has an acitve-low rst and will rst to 0 and count up to 15 and then roll over
		back to 0. The rst is also an asynchronous rst, and so can interupt the count at any time.

	Inputs:
		Clock: The internal System Clock. Typically 50MHz on the DE1-SoC boards
		rst: An active-low rst signal, supplied by a KEY on the DE1 board

	Outputs:
		outBus: The binary representation of the count that will be linked to LEDs on the DE1 board

	Contributors: Titus Berndt, Nesta Isakovic, and Joshua Shackelford

***********************************************************************************************/

//include additional modules for iVerilog
`include "DFlipFlop.v"

module RippleUp_Top(clk, rst, outBus);

	input clk, rst;
	output [3:0] outBus;
	
	//All internal wiring
	wire Q1Bar, Q2Bar, Q3Bar, Q4Bar;
	
	//The first DFF gets a signal from the clock, the rest toggle on the rising edge of the
	//qBar signal of the previous DFF
	DFlipFlop F1 (.q(outBus[0]), .qBar(Q1Bar), .D(Q1Bar), .clk(clk), .rst(rst));
	DFlipFlop F2 (.q(outBus[1]), .qBar(Q2Bar), .D(Q2Bar), .clk(Q1Bar), .rst(rst));
	DFlipFlop F3 (.q(outBus[2]), .qBar(Q3Bar), .D(Q3Bar), .clk(Q2Bar), .rst(rst));
	DFlipFlop F4 (.q(outBus[3]), .qBar(Q4Bar), .D(Q4Bar), .clk(Q3Bar), .rst(rst));
	
endmodule

Ripple_iVerilog/RippleUp_testbench.v
/***********************************************************************************************
	EE 371
	Joshua Smith
	Section AB

	Description:
		RippleUp_testbench.v is the tester module for RippleUp_Top. It is writen to be compiled
		by iVerilog and simulated in GTKWave.

	Inputs:
		None

	Outputs:
		None

	Author: Joshua Shackelford

***********************************************************************************************/

//include additional modules for iVerilog
`include "RippleUp_Top.v"

module RippleUp_testbench();

	reg Clock, Reset;
	wire [3:0] outBus;
	parameter CLOCK_PERIOD = 10;
		
	//Set Clock	
	initial
	begin
		Clock <= 0;
		forever #(CLOCK_PERIOD/2) Clock <= ~Clock;
	end

   	RippleUp_Top dut (Clock, Reset, outBus);

	//Set files for GTKWave
    initial
    begin
        $dumpfile("RippleUp.vcd");
        $dumpvars(1, dut);
    end
	
	//Let the counter run
	initial
	begin
		Reset <= 0;	#10;
		Reset <= 1;	#10;
		repeat(50)	#10;
		Reset <= 0;	#10;
		Reset <= 1;	#10;
		repeat(25)	#10;
		$finish;
	end
	

endmodule

Ripple_iVerilog/RippleUp.vcd
$date
	Tue Apr 11 09:46:11 2017
$end
$version
	Icarus Verilog
$end
$timescale
	1s
$end
$scope module RippleUp_testbench $end
$scope module dut $end
$var wire 1 ! clk $end
$var wire 1 " rst $end
$var wire 4 # outBus [3:0] $end
$var wire 1 $ Q4Bar $end
$var wire 1 % Q3Bar $end
$var wire 1 & Q2Bar $end
$var wire 1 ' Q1Bar $end
$upscope $end
$upscope $end
$enddefinitions $end
#0
$dumpvars
1'
1&
1%
1$
b0 #
0"
0!
$end
#5
1!
#10
0!
1"
#15
0'
b1 #
1!
#20
0!
#25
0&
1'
b10 #
1!
#30
0!
#35
0'
b11 #
1!
#40
0!
#45
0%
1&
1'
b100 #
1!
#50
0!
#55
0'
b101 #
1!
#60
0!
#65
0&
1'
b110 #
1!
#70
0!
#75
0'
b111 #
1!
#80
0!
#85
0$
1%
1&
1'
b1000 #
1!
#90
0!
#95
0'
b1001 #
1!
#100
0!
#105
0&
1'
b1010 #
1!
#110
0!
#115
0'
b1011 #
1!
#120
0!
#125
0%
1&
1'
b1100 #
1!
#130
0!
#135
0'
b1101 #
1!
#140
0!
#145
0&
1'
b1110 #
1!
#150
0!
#155
0'
b1111 #
1!
#160
0!
#165
1$
1%
1&
1'
b0 #
1!
#170
0!
#175
0'
b1 #
1!
#180
0!
#185
0&
1'
b10 #
1!
#190
0!
#195
0'
b11 #
1!
#200
0!
#205
0%
1&
1'
b100 #
1!
#210
0!
#215
0'
b101 #
1!
#220
0!
#225
0&
1'
b110 #
1!
#230
0!
#235
0'
b111 #
1!
#240
0!
#245
0$
1%
1&
1'
b1000 #
1!
#250
0!
#255
0'
b1001 #
1!
#260
0!
#265
0&
1'
b1010 #
1!
#270
0!
#275
0'
b1011 #
1!
#280
0!
#285
0%
1&
1'
b1100 #
1!
#290
0!
#295
0'
b1101 #
1!
#300
0!
#305
0&
1'
b1110 #
1!
#310
0!
#315
0'
b1111 #
1!
#320
0!
#325
1$
1%
1&
1'
b0 #
1!
#330
0!
#335
0'
b1 #
1!
#340
0!
#345
0&
1'
b10 #
1!
#350
0!
#355
0'
b11 #
1!
#360
0!
#365
0%
1&
1'
b100 #
1!
#370
0!
#375
0'
b101 #
1!
#380
0!
#385
0&
1'
b110 #
1!
#390
0!
#395
0'
b111 #
1!
#400
0!
#405
0$
1%
1&
1'
b1000 #
1!
#410
0!
#415
0'
b1001 #
1!
#420
0!
#425
0&
1'
b1010 #
1!
#430
0!
#435
0'
b1011 #
1!
#440
0!
#445
0%
1&
1'
b1100 #
1!
#450
0!
#455
0'
b1101 #
1!
#460
0!
#465
0&
1'
b1110 #
1!
#470
0!
#475
0'
b1111 #
1!
#480
0!
#485
1$
1%
1&
1'
b0 #
1!
#490
0!
#495
0'
b1 #
1!
#500
0!
#505
0&
1'
b10 #
1!
#510
0!
#515
0'
b11 #
1!
#520
1'
1&
b0 #
0!
0"
#525
1!
#530
0!
1"
#535
0'
b1 #
1!
#540
0!
#545
0&
1'
b10 #
1!
#550
0!
#555
0'
b11 #
1!
#560
0!
#565
0%
1&
1'
b100 #
1!
#570
0!
#575
0'
b101 #
1!
#580
0!
#585
0&
1'
b110 #
1!
#590
0!
#595
0'
b111 #
1!
#600
0!
#605
0$
1%
1&
1'
b1000 #
1!
#610
0!
#615
0'
b1001 #
1!
#620
0!
#625
0&
1'
b1010 #
1!
#630
0!
#635
0'
b1011 #
1!
#640
0!
#645
0%
1&
1'
b1100 #
1!
#650
0!
#655
0'
b1101 #
1!
#660
0!
#665
0&
1'
b1110 #
1!
#670
0!
#675
0'
b1111 #
1!
#680
0!
#685
1$
1%
1&
1'
b0 #
1!
#690
0!
#695
0'
b1 #
1!
#700
0!
#705
0&
1'
b10 #
1!
#710
0!
#715
0'
b11 #
1!
#720
0!
#725
0%
1&
1'
b100 #
1!
#730
0!
#735
0'
b101 #
1!
#740
0!
#745
0&
1'
b110 #
1!
#750
0!
#755
0'
b111 #
1!
#760
0!
#765
0$
1%
1&
1'
b1000 #
1!
#770
0!
#775
0'
b1001 #
1!
#780
0!
#785
0&
1'
b1010 #
1!
